Workbook

Sheet Read me
A1: How to translate: fill the 'translation' column. Leave it empty to keep the English.
A2: Each row is one unique English text (per tab); 'uses' = how many game entries share it, all get your translation.
A3: Do not edit file / label (first entry using the text). location / speaker are guesses from the label name.
A4: Entries with nothing to translate (only codes or symbols) are left out and stay as they are.
A6: Codes inside the text:
A7: line break = a real line break in the cell (Alt+Enter in Excel)
A8: [p] = new page (waits for a button press)
A9: [s] = scroll one line
A10: [0] [1] ... = placeholders (player name, Pokémon, item, number...). Move them freely, keep them.
A11: [w:0.2] [e:4] = pauses / timed effects. Keep them.
A12: <color=...>...</color>, <size=...>, <pos=...> = text formatting. Keep them.
A13: {ele|ela} = depends on the PLAYER's gender: male text | female text. Ex: Você é um{|a} ótim{o|a} Treinador{|a}!
... A17: [[ and {{ = a literal [ or { character.

Sheet Names
A1: file | B1: label | C1: location | D1: speaker | E1: english | F1: translation | G1: uses
A2: english_dp_underground_name_plural_classified | B2: UNDERGROUND_NAME_001 | E2: Red Spheres S | F2: Esferas Vermelhas P | G2: 3
A3: english_dp_underground_name_plural_classified | B3: UNDERGROUND_NAME_002 | E3: Blue Spheres S | F3: Esferas Azuis P | G3: 2
A4: english_dp_underground_name_plural_classified | B4: UNDERGROUND_NAME_003 | E4: Green Spheres S | F4: Esferas Verdes P | G4: 2
A5: english_dp_underground_name_plural_classified | B5: UNDERGROUND_NAME_004 | E5: Prism Spheres S | F5: Esferas Prismáticas P | G5: 2
A6: english_dp_underground_name_plural_classified | B6: UNDERGROUND_NAME_005 | E6: Pale Spheres S | F6: Esferas Pálidas P | G6: 2
A7: english_dp_underground_name_plural_classified | B7: UNDERGROUND_NAME_006 | E7: Red Spheres L | F7: Esferas Vermelhas G | G7: 2
A8: english_dp_underground_name_plural_classified | B8: UNDERGROUND_NAME_007 | E8: Blue Spheres L | F8: Esferas Azuis G | G8: 2
A9: english_dp_underground_name_plural_classified | B9: UNDERGROUND_NAME_008 | E9: Green Spheres L | F9: Esferas Verdes G | G9: 2
A10: english_dp_underground_name_plural_classified | B10: UNDERGROUND_NAME_009 | E10: Prism Spheres L | F10: Esferas Prismáticas G | G10: 2
A11: english_dp_underground_name_plural_classified | B11: UNDERGROUND_NAME_010 | E11: Pale Spheres L | F11: Esferas Pálidas G | G11: 2
A12: english_dp_underground_name_plural_classified | B12: UNDERGROUND_NAME_011 | E12: Revives | F12: Reviveres | G12: 4
A13: english_dp_underground_name_plural_classified | B13: UNDERGROUND_NAME_012 | E13: Max Revives | F13: Reviveres Máx. | G13: 4
... A106: english_dp_underground_name_plural_classified | B106: UNDERGROUND_NAME_399 | E106: Digger Drills | F106: Brocas Escavadoras | G106: 4
A107: english_dp_underground_name_plural_classified | B107: UNDERGROUND_NAME_400 | E107: TM01s | G107: 4
A108: english_dp_underground_name_plural_classified | B108: UNDERGROUND_NAME_401 | E108: TM02s | G108: 4
A109: english_dp_underground_name_plural_classified | B109: UNDERGROUND_NAME_402 | E109: TM03s | G109: 4
A110: english_dp_underground_name_plural_classified | B110: UNDERGROUND_NAME_403 | E110: TM04s | G110: 4
A111: english_dp_underground_name_plural_classified | B111: UNDERGROUND_NAME_404 | E111: TM05s | G111: 4
A112: english_dp_underground_name_plural_classified | B112: UNDERGROUND_NAME_405 | E112: TM06s | G112: 4
A113: english_dp_underground_name_plural_classified | B113: UNDERGROUND_NAME_406 | E113: TM07s | G113: 4
A114: english_dp_underground_name_plural_classified | B114: UNDERGROUND_NAME_407 | E114: TM08s | G114: 4
A115: english_dp_underground_name_plural_classified | B115: UNDERGROUND_NAME_408 | E115: TM09s | G115: 4
A116: english_dp_underground_name_plural_classified | B116: UNDERGROUND_NAME_409 | E116: TM10s | G116: 4
A117: english_dp_underground_name_plural_classified | B117: UNDERGROUND_NAME_410 | E117: TM11s | G117: 4
A118: english_dp_underground_name_plural_classified | B118: UNDERGROUND_NAME_411 | E118: TM12s | G118: 4
... A198: english_dp_underground_name_plural_classified | B198: UNDERGROUND_NAME_491 | E198: TM92s | G198: 4
A199: english_dp_underground_name_plural_classified | B199: UNDERGROUND_NAME_492 | E199: Bulbasaur Statues | F199: Estátuas de Bulbasauro | G199: 2
A200: english_dp_underground_name_plural_classified | B200: UNDERGROUND_NAME_493 | E200: Ivysaur Statues | F200: Estátuas de Ivysauro | G200: 2
A201: english_dp_underground_name_plural_classified | B201: UNDERGROUND_NAME_494 | E201: Venusaur Statues | F201: Estátuas de Venusauro | G201: 2
A202: english_dp_underground_name_plural_classified | B202: UNDERGROUND_NAME_495 | E202: Charmander Statues | F202: Estátuas de Charmander | G202: 2
A203: english_dp_underground_name_plural_classified | B203: UNDERGROUND_NAME_496 | E203: Charmeleon Statues | F203: Estátuas de Charmeleon | G203: 2
A204: english_dp_underground_name_plural_classified | B204: UNDERGROUND_NAME_497 | E204: Charizard Statues | F204: Estátuas de Charizard | G204: 2
A205: english_dp_underground_name_plural_classified | B205: UNDERGROUND_NAME_498 | E205: Squirtle Statues | F205: Estátuas de Squirtle | G205: 2
A206: english_dp_underground_name_plural_classified | B206: UNDERGROUND_NAME_499 | E206: Wartortle Statues | F206: Estátuas de Wartortle | G206: 2
A207: english_dp_underground_name_plural_classified | B207: UNDERGROUND_NAME_500 | E207: Blastoise Statues | F207: Estátuas de Blastoise | G207: 2
A208: english_dp_underground_name_plural_classified | B208: UNDERGROUND_NAME_501 | E208: Pikachu Statues | F208: Estátuas de Pikachu | G208: 2
A209: english_dp_underground_name_plural_classified | B209: UNDERGROUND_NAME_502 | E209: Nidoqueen Statues | F209: Estátuas de Nidoqueen | G209: 2
A210: english_dp_underground_name_plural_classified | B210: UNDERGROUND_NAME_503 | E210: Nidoking Statues | F210: Estátuas de Nidoking | G210: 2
... A621: english_dp_underground_name_plural_classified | B621: UNDERGROUND_NAME_1096 | E621: Rotom Statues  | F621: Estátuas de Rotom  | G621: 12
A622: english_dp_underground_name_plural_classified | B622: UNDERGROUND_NAME_1102 | E622: TM93s | G622: 6
A623: english_dp_underground_name_plural_classified | B623: UNDERGROUND_NAME_1103 | E623: TM94s | G623: 6
A624: english_dp_underground_name_plural_classified | B624: UNDERGROUND_NAME_1104 | E624: TM95s | G624: 6
A625: english_dp_underground_name_plural_classified | B625: UNDERGROUND_NAME_1105 | E625: TM96s | G625: 6
A626: english_dp_underground_name_plural_classified | B626: UNDERGROUND_NAME_1106 | E626: TM97s | G626: 6
A627: english_dp_underground_name_plural_classified | B627: UNDERGROUND_NAME_1107 | E627: TM98s | G627: 6
A628: english_dp_underground_name_plural_classified | B628: UNDERGROUND_NAME_1108 | E628: TM99s | G628: 6
A629: english_dp_underground_name_plural_classified | B629: UNDERGROUND_NAME_1109 | E629: TM100s | G629: 6
A630: english_dp_underground_name_plural_classified | B630: UNDERGROUND_NAME_1110 | E630: Square Pedestals XL | F630: Pedestais Quadrados GG | G630: 2
A631: english_dp_underground_name_plural_classified | B631: UNDERGROUND_NAME_1111 | E631: Round Pedestals XL | F631: Pedestais Redondos GG | G631: 2
A632: english_dp_underground_name_plural_classified | B632: UNDERGROUND_NAME_1112 | E632: Sturdy Pedestals XL | F632: Pedestais Robustos GG | G632: 2
A633: english_dp_underground_name_plural_classified | B633: UNDERGROUND_NAME_1113 | E633: Clear Pedestals XL | F633: Pedestais Transparentes GG | G633: 2
A634: english_dp_underground_name_plural_classified | B634: UNDERGROUND_NAME_1114 | E634: Spin Pedestals XL | F634: Pedestais Giratórios GG | G634: 2
A635: english_dp_underground_name_plural_classified | B635: UNDERGROUND_NAME_1115 | E635: Spinback Pedestals XL | F635: Pedestais Giratórios Inv. GG | G635: 2
A636: english_ss_fld_dressup_item_name | B636: SS_fld_dressup_item_name_000 | E636: Tops | F636: Partes de Cima | G636: 1
A637: english_ss_fld_dressup_item_name | B637: SS_fld_dressup_item_name_001 | E637: Outerwear | F637: Agasalhos | G637: 1
A638: english_ss_fld_dressup_item_name | B638: SS_fld_dressup_item_name_930 | E638: Pikachu Hoodie Style | F638: Estilo Moletom de Pikachu | G638: 1
A639: english_ss_fld_dressup_item_name | B639: SS_fld_dressup_item_name_931 | E639: Platinum Style | F639: Estilo Platinum | G639: 1
A640: english_ss_fld_dressup_item_name | B640: SS_fld_dressup_item_name_932 | E640: Overalls Style | F640: Estilo Jardineira | G640: 1
A641: english_ss_fld_dressup_item_name | B641: SS_fld_dressup_item_name_933 | E641: Eevee Jacket Style | F641: Estilo Jaqueta de Eevee | G641: 1
... A1676: english_ss_itemname_acc | B1676: ITEMNAME_1134 | E1676: TM105 | F1676: MT105 | G1676: 4
A1677: english_ss_itemname_acc | B1677: ITEMNAME_1135 | E1677: TR05 | G1677: 4
A1678: english_ss_itemname_acc | B1678: ITEMNAME_1136 | E1678: TR06 | G1678: 4
A1679: english_ss_itemname_acc | B1679: ITEMNAME_1137 | E1679: TR07 | G1679: 4
A1680: english_ss_itemname_acc | B1680: ITEMNAME_1138 | E1680: TR08 | G1680: 4
A1681: english_ss_itemname_acc | B1681: ITEMNAME_1139 | E1681: TR09 | G1681: 4
A1682: english_ss_itemname_acc | B1682: ITEMNAME_1140 | E1682: TR10 | G1682: 4
A1683: english_ss_itemname_acc | B1683: ITEMNAME_1141 | E1683: TR11 | G1683: 4
A1684: english_ss_itemname_acc | B1684: ITEMNAME_1142 | E1684: TR12 | G1684: 4
A1685: english_ss_itemname_acc | B1685: ITEMNAME_1143 | E1685: TR13 | G1685: 4
A1686: english_ss_itemname_acc | B1686: ITEMNAME_1144 | E1686: TR14 | G1686: 4
A1687: english_ss_itemname_acc | B1687: ITEMNAME_1145 | E1687: TR15 | G1687: 4
A1688: english_ss_itemname_acc | B1688: ITEMNAME_1146 | E1688: TR16 | G1688: 4
... A1771: english_ss_itemname_acc | B1771: ITEMNAME_1229 | E1771: TR99 | G1771: 4
A1772: english_ss_itemname_acc | B1772: ITEMNAME_1230 | E1772: TM00 | F1772: MT00 | G1772: 4
A1773: english_ss_itemname_acc | B1773: ITEMNAME_1231 | E1773: Lonely Mint | F1773: Menta Carente | G1773: 2
A1774: english_ss_itemname_acc | B1774: ITEMNAME_1232 | E1774: Adamant Mint | F1774: Menta Firme | G1774: 2
A1775: english_ss_itemname_acc | B1775: ITEMNAME_1233 | E1775: Naughty Mint | F1775: Menta Sapeca | G1775: 2
A1776: english_ss_itemname_acc | B1776: ITEMNAME_1234 | E1776: Brave Mint | F1776: Menta Valente | G1776: 2
A1777: english_ss_itemname_acc | B1777: ITEMNAME_1235 | E1777: Bold Mint | F1777: Menta Audaciosa | G1777: 2
A1778: english_ss_itemname_acc | B1778: ITEMNAME_1236 | E1778: Impish Mint | F1778: Menta Rebelde | G1778: 2
A1779: english_ss_itemname_acc | B1779: ITEMNAME_1237 | E1779: Lax Mint | F1779: Menta Negligente | G1779: 2
A1780: english_ss_itemname_acc | B1780: ITEMNAME_1238 | E1780: Relaxed Mint | F1780: Menta Relaxada | G1780: 2
A1781: english_ss_itemname_acc | B1781: ITEMNAME_1239 | E1781: Modest Mint | F1781: Menta Modesta | G1781: 2
A1782: english_ss_itemname_acc | B1782: ITEMNAME_1240 | E1782: Mild Mint | F1782: Menta Tranquila | G1782: 2
A1783: english_ss_itemname_acc | B1783: ITEMNAME_1241 | E1783: Rash Mint | F1783: Menta Rabugenta | G1783: 2
... A9556: english_ss_zkn_form | B9556: ZKN_FORM_999_001 | E9556: Roaming Form | F9556: Forma Perambulante | G9556: 1

Sheet Menus & UI
A1: file | B1: label | C1: location | D1: speaker | E1: english | F1: translation | G1: uses
A2: english_ss_status | B2: SS_status_02 | E2: Lv. [0] | F2: Nv. [0] | G2: 11
A3: english_ss_status | B3: SS_status_03 | E3: Name | F3: Nome | G3: 3
A4: english_ss_status | B4: SS_status_06 | E4: Original Trainer | F4: Treinador Original | G4: 2
A5: english_ss_status | B5: SS_status_09 | E5: ID No. | F5: Nº ID | G5: 2
A6: english_ss_status | B6: SS_status_90 | E6: Pokédex No. | F6: Nº Pokédex | G6: 1
A7: english_ss_status | B7: SS_status_12 | E7: Current Exp. Points | F7: Pontos de Exp. atuais | G7: 1
A8: english_ss_status | B8: SS_status_15 | E8: Points needed to level up | F8: Pontos para subir de nível | G8: 1
A9: english_ss_status | B9: SS_status_20 | E9: Held Item | F9: Item Segurado | G9: 3
A10: english_ss_status | B10: SS_status_23 | E10: Held Item | F10: Item Segurado | G10: 1
A11: english_ss_status | B11: SS_status_24 | E11: Change Markings | F11: Mudar Marcações | G11: 1
A12: english_ss_status | B12: SS_status_25 | E12: Back | F12: Voltar | G12: 18
A13: english_ss_status | B13: SS_status_28 | E13: HP | F13: PS | G13: 5
... A1961: english_ss_pokedex | B1961: SS_pokedex_196 | E1961: 83.8 lbs. | F1961: 38,0 kg | G1961: 1

Sheet Descriptions
A1: file | B1: label | C1: location | D1: speaker | E1: english | F1: translation | G1: uses
A2: english_ss_trainermemo | B2: SS_trainermemo_001 | E2: This Pokémon is pretty <color=#F01E1EFF>Hardy</color> by nature. | F2: Este Pokémon tem uma natureza bem <color=#F01E1EFF>Destemida</color>. | G2: 1
A3: english_ss_trainermemo | B3: SS_trainermemo_002 | E3: This Pokémon is pretty <color=#F01E1EFF>Lonely</color> by nature. | F3: Este Pokémon tem uma natureza bem <color=#F01E1EFF>Solitária</color>. | G3: 1
A4: english_ss_trainermemo | B4: SS_trainermemo_003 | E4: This Pokémon is pretty <color=#F01E1EFF>Brave</color> by nature. | F4: Este Pokémon tem uma natureza bem <color=#F01E1EFF>Valente</color>. | G4: 1
A5: english_ss_trainermemo | B5: SS_trainermemo_004 | E5: This Pokémon is pretty <color=#F01E1EFF>Adamant</color> by nature. | F5: Este Pokémon tem uma natureza bem <color=#F01E1EFF>Rígida</color>. | G5: 1
A6: english_ss_trainermemo | B6: SS_trainermemo_005 | E6: This Pokémon is pretty <color=#F01E1EFF>Naughty</color> by nature. | F6: Este Pokémon tem uma natureza bem <color=#F01E1EFF>Teimosa</color>. | G6: 1
A7: english_ss_trainermemo | B7: SS_trainermemo_006 | E7: This Pokémon is pretty <color=#F01E1EFF>Bold</color> by nature. | F7: Este Pokémon tem uma natureza bem <color=#F01E1EFF>Corajosa</color>. | G7: 1
A8: english_ss_trainermemo | B8: SS_trainermemo_007 | E8: This Pokémon is pretty <color=#F01E1EFF>Docile</color> by nature. | F8: Este Pokémon tem uma natureza bem <color=#F01E1EFF>Dócil</color>. | G8: 1
A9: english_ss_trainermemo | B9: SS_trainermemo_008 | E9: This Pokémon is pretty <color=#F01E1EFF>Relaxed</color> by nature. | F9: Este Pokémon tem uma natureza bem <color=#F01E1EFF>Descontraída</color>. | G9: 1
A10: english_ss_trainermemo | B10: SS_trainermemo_009 | E10: This Pokémon is pretty <color=#F01E1EFF>Impish</color> by nature. | F10: Este Pokémon tem uma natureza bem <color=#F01E1EFF>Inquieta</color>. | G10: 1
A11: english_ss_trainermemo | B11: SS_trainermemo_010 | E11: This Pokémon is pretty <color=#F01E1EFF>Lax</color> by nature. | F11: Este Pokémon tem uma natureza bem <color=#F01E1EFF>Relaxada</color>. | G11: 1
A12: english_ss_trainermemo | B12: SS_trainermemo_011 | E12: This Pokémon is pretty <color=#F01E1EFF>Timid</color> by nature. | F12: Este Pokémon tem uma natureza bem <color=#F01E1EFF>Tímida</color>. | G12: 1
A13: english_ss_trainermemo | B13: SS_trainermemo_012 | E13: This Pokémon is pretty <color=#F01E1EFF>Hasty</color> by nature. | F13: Este Pokémon tem uma natureza bem <color=#F01E1EFF>Apressada</color>. | G13: 1
... A3512: english_dp_pokedex_pearl | B3512: DP_pokedex_pearl_264_001 | E3512: It uses its long tongue to taunt opponents. Once the opposition is enraged, this Pokémon hurls[p]itself at the opponent, tackling them forcefully. | F3512: Mostra sua língua comprida para provocar o oponente e, quando o alvo perde a cabeça de[p]raiva, joga-se contra ele em uma investida violenta. | G3512: 2

Sheet Dialogue
A1: file | B1: label | C1: location | D1: speaker | E1: english | F1: translation | G1: uses
A2: english_dp_contest | B2: DP_contest_000 | E2: Dummy message | F2: Mensagem de teste | G2: 1
A3: english_dp_contest | B3: DP_contest_688 | E3: Oh? It seems you don’t have a Pokémon that can enter a contest show.[p]Please come back with a Pokémon that knows a move that can be used in contest shows. | F3: Oh? Parece que você não tem nenhum Pokémon que possa participar de um Concurso.[p]Por favor, volte com um Pokémon que conheça um movimento válido para os Concursos. | G3: 1
A4: english_dp_contest | B4: DP_contest_032 | E4: That’s it, folks! All evaluations have been tallied and totaled! Which Pokémon will be crowned the[s]Star of the Show? Let’s announce the results! | F4: E é isso aí, pessoal! Todas as notas foram somadas e calculadas! Qual Pokémon será coroado a[s]Estrela do Show? Vamos aos resultados! | G4: 1
A5: english_dp_contest | B5: DP_contest_118 | E5: Coolness Contest | F5: Concurso de Carisma | G5: 3
A6: english_dp_contest | B6: DP_contest_119 | E6: Beauty Contest | F6: Concurso de Beleza | G6: 3
A7: english_dp_contest | B7: DP_contest_120 | E7: Cuteness Contest | F7: Concurso de Fofura | G7: 3
A8: english_dp_contest | B8: DP_contest_121 | E8: Cleverness Contest | F8: Concurso de Astúcia | G8: 3
A9: english_dp_contest | B9: DP_contest_122 | E9: Toughness Contest | F9: Concurso de Vigor | G9: 3
A10: english_dp_contest | B10: DP_contest_123 | E10: Normal Rank | F10: Ranque Normal | G10: 3
A11: english_dp_contest | B11: DP_contest_124 | E11: Great Rank | F11: Ranque Grande | G11: 3
A12: english_dp_contest | B12: DP_contest_125 | E12: Ultra Rank | F12: Ranque Ultra | G12: 3
A13: english_dp_contest | B13: DP_contest_126 | E13: Master Rank | F13: Ranque Mestre | G13: 3
... A205: english_dp_contest | B205: 00_msg_r212ar0101_msg_35 | E205: Oh, hey. Nice job, kiddo.[p]You met the requirement alright. But who said we have to keep promises![p]Fwahahaha... | F205: Ora, ora. Mandou bem, pirralh{o|a}.[p]Você cumpriu a nossa exigência direitinho. Mas quem disse que a gente cumpre promessas?[p]Fuahahaha... | G205: 2
A206: english_dp_trainer_msg_sub | B206: 35-msg_c01r0201_idol_01 | C206: Jubilife City | D206: idol | E206: More than singing! More than dancing! I love Pokémon! So, shall we battle? | F206: Mais do que cantar! Mais do que dançar! Eu amo Pokémon! E aí, vamos batalhar? | G206: 1
A207: english_dp_trainer_msg_sub | B207: 35-msg_c01r0201_idol_02 | C207: Jubilife City | D207: idol | E207: I’ll let you join my fan club if you can beat me! | F207: Deixo você entrar no meu fã-clube se me vencer! | G207: 2
A208: english_dp_trainer_msg_sub | B208: 35-msg_c01r0201_idol_03 | C208: Jubilife City | D208: idol | E208: Aww, that’s heartbreaking... I’m an idol, too... | F208: Ah, você partiu meu coração... E olha que sou uma idol... | G208: 1
A209: english_dp_trainer_msg_sub | B209: 35-msg_c01r0201_idol_04 | C209: Jubilife City | D209: idol | E209: Well, that’s me and my Pokémon! Thank you for being such a fan![p]Just so you know, our latest single is called “Jigglin’ Pokémon Wub”! | F209: Bom, esses somos eu e o meu Pokémon! Obrigada por ser tão fã![p]E só pra você saber, nosso single mais recente se chama 'Pokémon no Batidão'! | G209: 2
A210: english_dp_trainer_msg_sub | B210: 35-msg_c01r0201_reporter_01 | C210: Jubilife City | D210: reporter | E210: I’m working on a story. Can you battle me? | F210: Estou fazendo uma matéria. Pode batalhar comigo? | G210: 1
A211: english_dp_trainer_msg_sub | B211: 35-msg_c01r0201_reporter_02 | C211: Jubilife City | D211: reporter | E211: Join me for a live report! | F211: Participe da minha transmissão ao vivo! | G211: 1
A212: english_dp_trainer_msg_sub | B212: 35-msg_c01r0201_reporter_03 | C212: Jubilife City | D212: reporter | E212: Press coverage denied... But you’re so intriguing! | F212: Cobertura de imprensa negada... Mas você é tão intrigante! | G212: 1
A213: english_dp_trainer_msg_sub | B213: 35-msg_c01r0201_reporter_04 | C213: Jubilife City | D213: reporter | E213: Interviews are about taking the initiative. | F213: Em uma entrevista, o segredo é tomar a iniciativa. | G213: 2
A214: english_dp_trainer_msg_sub | B214: 35-msg_c01r0201_cameraman_01 | C214: Jubilife City | D214: cameraman | E214: I’ve spotted a charismatic Trainer! Is it OK to go for the scoop? | F214: Avistei um{|a} Treinador{|a} cheio de carisma! Posso registrar esse furo? | G214: 1
A215: english_dp_trainer_msg_sub | B215: 35-msg_c01r0201_cameraman_02 | C215: Jubilife City | D215: cameraman | E215: As a professional cameraman, I always go for the best shot! | F215: Como cinegrafista profissional, estou sempre em busca do melhor ângulo! | G215: 1
A216: english_dp_trainer_msg_sub | B216: 35-msg_c01r0201_cameraman_03 | C216: Jubilife City | D216: cameraman | E216: That’s a downer... I thought I’d found a Trainer and Pokémon who’d shine on camera. | F216: Que balde de água fria... Achei que tinha encontrado um{|a} Treinador{|a} e um Pokémon que brilhariam na tela. | G216: 1
A217: english_dp_trainer_msg_sub | B217: 35-msg_c01r0201_cameraman_04 | C217: Jubilife City | D217: cameraman | E217: The lively expressions on you and your Pokémon’s faces make for some great TV! | F217: As expressões cheias de vida no seu rosto e no do seu Pokémon rendem ótimas cenas pra TV! | G217: 2
... A430: english_dp_trainer_msg_sub | B430: 115-msg_l02r0101_0903b_04 | C430: Valor Lakefront | D430: 0903b | E430: Don’t fret, dear. If we take in too many calories, we can always work them off by battling! | F430: Não se preocupe, querido. Se consumirmos calorias demais, sempre podemos queimá-las batalhando! | G430: 1
A431: english_dp_trainer_msg_sub | B431: 1-ARTIST_03_TRMSG_FIGHT_LOSE | D431: Artist Ismael | E431: Does this mean I’m only talented as an artist? | F431: Isso significa que meu único talento é como artista? | G431: 1
A432: english_dp_trainer_msg_sub | B432: 1-SISTER_10_TRMSG_FIGHT_LOSE | D432: Beauty Gabriella | E432: You’re a lucky one... | F432: Você deu sorte... | G432: 1
A433: english_dp_trainer_msg_sub | B433: 1-PRINCE_06_TRMSG_FIGHT_LOSE | D433: Rich Boy Roman | E433: I never thought I’d lose at Father’s restaurant... | F433: Nunca pensei que perderia no restaurante do meu pai... | G433: 1
A434: english_dp_trainer_msg_sub | B434: 1-PRINCESS_04_TRMSG_FIGHT_LOSE | D434: Lady Kylie | E434: Oh... How could I lose at dear Papa’s restaurant? | F434: Oh... Como pude perder no restaurante do meu querido papai? | G434: 1
A435: english_dp_trainer_msg_sub | B435: 1-GENTLE_03_TRMSG_FIGHT_LOSE | D435: Gentleman Leonardo | E435: Ack! I lost... Check, please! | F435: Argh! Eu perdi... A conta, por favor! | G435: 1
A436: english_dp_trainer_msg_sub | B436: 1-MADAM_03_TRMSG_FIGHT_LOSE | D436: Madame Rebecca | E436: So young, and yet so strong! How very remarkable! | F436: Tão jovem, e ainda assim tão forte! Simplesmente notável! | G436: 1
A437: english_dp_trainer_msg_sub | B437: 1-COLLECTOR_10_TRMSG_FIGHT_LOSE | D437: Collector Eugene | E437: I don’t care if I lose. I’m still a happy guy. | F437: Não ligo se perdi. Continuo sendo um cara feliz. | G437: 1
A438: english_dp_trainer_msg_sub | B438: 1-AROMA_06_TRMSG_FIGHT_LOSE | D438: Aroma Lady Alison | E438: Waaah! You’re too much! | F438: Buááá! Você é demais pra mim! | G438: 1
A439: english_dp_trainer_msg_sub | B439: 1-SCHOOLB_06_TRMSG_FIGHT_LOSE | D439: School Kid Esteban | E439: Wow... You’re out there. | F439: Uau... Você é de outro mundo. | G439: 1
A440: english_dp_trainer_msg_sub | B440: 1-DAISUKIW_05_TRMSG_FIGHT_LOSE | D440: Poké Fan Meredith | E440: No one’s hurt? | F440: Ninguém se machucou? | G440: 1
A441: english_dp_trainer_msg_sub | B441: 1-VETERAN_11_TRMSG_FIGHT_LOSE | D441: Veteran Emanuel | E441: Tough, aren’t you...? | F441: Você é dur{ão|ona} na queda, hein...? | G441: 1
A442: english_dp_trainer_msg_sub | B442: 1-MINI_13_TRMSG_FIGHT_LOSE | D442: Lass Blythe | E442: I was with my dad, too... | F442: E olha que eu estava com o meu pai... | G442: 1
... A450: english_dp_trainer_msg_sub | B450: 1-SCHOOLG_04_TRMSG_FIGHT_LOSE | D450: School Kid Christine | E450: I like to study a lot. I thought I could win... | F450: Eu gosto muito de estudar. Achei que fosse vencer... | G450: 1
A451: english_dp_trainer_msg_sub | B451: 00_msg_c01r0701_trainer_boy_06 | C451: Trainers’ School | D451: trainer | E451: A Technical Machine, or TM for short, contains a Pokémon move.[p]Using a TM, you can instantly teach its move to a Pokémon.[p]You’ll find you receive lots of copies of a TM when you obtain it.[p]Don’t be shy to use them! | F451: Uma Máquina Técnica, ou MT para encurtar, contém um movimento Pokémon.[p]Usando uma MT, você pode ensinar o movimento dela a um Pokémon na mesma hora.[p]Você vai ver que recebe várias cópias de uma MT quando a encontra.[p]Então não tenha medo de usar! | G451: 1
A452: english_dp_tvshow | B452: 106-msg_tv_02_01_01_1 | D452: TV | E452: Gotta catch ’em all! It’s the Catch That Pokémon Show![p]So, let me tell you about this show’s featured Pokémon-catching Trainer. | F452: Temos que pegar! Começa agora o programa Pegue Aquele Pokémon![p]Então, deixem eu contar sobre {254:o Treinador|a Treinadora} especialista em capturas em destaque de hoje. | G452: 4
A453: english_dp_tvshow | B453: 106-msg_tv_02_01_01_2 | D453: TV | E453: The Trainer that caught our eye with a dandy of a catch is none other than the inestimable[s][0]! And what, you may ask[s]yourself, did [1] catch? Why, none[s]other than a mighty fine [2]! | F453: {254:O Treinador|A Treinadora} que chamou a nossa atenção com uma captura de mestre não é ninguém menos que {254:o|a}[s]inestimável [0]! E o que vocês acham que[s][1] capturou? Ora, nada mais, nada menos[s]que um belo [2]! | G453: 2
A454: english_dp_tvshow | B454: 106-msg_tv_02_01_01_3 | D454: TV | E454: Nice one, [0]! That’s one slick takedown![p]The Pokémon was nabbed with an expertly thrown [1].[p]And out of [2] used, it was the very last one! | F454: Mandou bem, [0]! Essa captura foi de cinema![p]O Pokémon foi pego com um arremesso perfeito de [1].[p]E de um total de [2], foi na última tentativa! | G454: 2
A455: english_dp_tvshow | B455: 106-msg_tv_02_01_01_4 | D455: TV | E455: Lame joking aside, we’re talking about one great Trainer in [0]![p]Oh? Hang on a second... I’ve got a hot new update! | F455: Piadas sem graça à parte, [0] é mesmo um{|a} grande Treinador{|a}![p]Hã? Esperem um segundo... Acabei de receber uma notícia quentíssima! | G455: 2
A456: english_dp_tvshow | B456: 106-msg_tv_02_01_01_5 | D456: TV | E456: We just got told what [0] nicknamed the caught [1]! | F456: Acabaram de nos informar o apelido que [0] deu para o [1] capturado! | G456: 1
A457: english_dp_tvshow | B457: 106-msg_tv_02_01_01_6 | D457: TV | E457: The nickname’s [0]! Yow, [1]![p]You’re the last word in cool! You’re so cool, you’re absolute zero! | F457: O apelido é [0]! Uau, [1]![p]Você é a definição de estilo! Você é tão maneir{254:o|a} que chega a ser abaixo de zero! | G457: 1
A458: english_dp_tvshow | B458: 106-msg_tv_02_01_01_7 | D458: TV | E458: Listen up, folks! You go out and emulate [0]! Get out there and catch[s]Pokémon like there’s no tomorrow! | F458: Escutem bem, pessoal! Saiam por aí e sigam o exemplo de [0]! Vão lá fora e capturem[s]Pokémon como se não houvesse amanhã! | G458: 1
A459: english_dp_tvshow | B459: 106-msg_tv_02_01_02_5 | D459: TV | E459: It turns out [0] opted not to nickname the [1]! | F459: Parece que [0] decidiu não dar apelido para o [1]! | G459: 1
A460: english_dp_tvshow | B460: 106-msg_tv_02_01_02_6 | D460: TV | E460: Yow, [0]! That is so nihilistically cool![p]Listen up, folks! You go out and emulate [1]! Get out there and catch[s]Pokémon like there’s no tomorrow! | F460: Uau, [0]! Esse desapego é tão estiloso![p]Escutem bem, pessoal! Saiam por aí e sigam o exemplo de [1]! Vão lá fora e capturem[s]Pokémon como se não houvesse amanhã! | G460: 1
A461: english_dp_tvshow | B461: 106-msg_tv_02_02_01_2 | D461: TV | E461: The Trainer that caught our eye with a dandy of a catch is none other than the inestimable[s][0]! And what, you may ask[s]yourself, did [1] catch?[p]The Pokémon was a— Huh? Hold on a moment... | F461: {254:O Treinador|A Treinadora} que chamou a nossa atenção com uma captura de mestre não é ninguém menos que {254:o|a}[s]inestimável [0]! E o que vocês acham que[s][1] capturou?[p]O Pokémon foi um... Hã? Esperem um momento... | G461: 2
A462: english_dp_tvshow | B462: 106-msg_tv_02_02_01_3 | D462: TV | E462: [0] blew this catch completely...[p]Not one ball out of the [1] thrown did the job... | F462: [0] deixou a captura escapar feio...[p]Nenhuma das [1] bolas arremessadas deu conta do recado... | G462: 1
A463: english_dp_tvshow | B463: 106-msg_tv_02_02_01_4 | D463: TV | E463: And [0] ended up making the quarry faint...[p]Oh, what a major downer. This is too tragic to be a good news piece... | F463: E [0] acabou fazendo o alvo desmaiar...[p]Ah, que balde de água fria. Isso é trágico demais para dar uma boa matéria... | G463: 1
... A915: english_dp_scenario1 | B915: 8-EV_POKESELECT_08 | D915: pokeselect | E915: Which one do you want, then? | F915: Qual deles você quer, então? | G915: 1
A916: english_dp_scenario1 | B916: 9-msg_r201_rival_a_01_1 | C916: Route 201 | D916: Barry | E916: Too slow! | F916: Lerd{o|a} demais! | G916: 2
A917: english_dp_scenario1 | B917: 9-msg_r201_rival_a_01_2 | C917: Route 201 | D917: Barry | E917: I’m sick of waiting! I’m going to go see Prof. Rowan, so I can thank him properly.[p]So, I had this great idea. | F917: Cansei de esperar! Eu vou lá ver o Prof. Rowan pra agradecer a ele direitinho.[p]Aí eu tive uma ideia genial. | G917: 1
A918: english_dp_scenario1 | B918: 9-msg_r201_rival_a_01_3 | C918: Route 201 | D918: Barry | E918: Listen up, OK? You know that lake where we always play at?[p]You know how they say a legendary Pokémon lives there?[p]You guessed it! | F918: Escuta só, tá? Sabe aquele lago onde a gente sempre brinca?[p]Sabe como dizem que um Pokémon lendário vive lá?[p]Isso mesmo que você pensou! | G918: 1
A919: english_dp_scenario1 | B919: 9-msg_r201_rival_a_01_4 | C919: Route 201 | D919: Barry | E919: We're going to catch that Pokémon. That’ll make Prof. Rowan happy.[p]I’m sure of that! | F919: A gente vai capturar esse Pokémon. Isso vai deixar o Prof. Rowan feliz da vida.[p]Tenho certeza absoluta! | G919: 1
A920: english_dp_scenario1 | B920: 9-msg_r201_rival_a_02 | C920: Route 201 | D920: Barry | E920: Hey! Where are you wandering off to?![p]That mystery Pokémon! It’s calling out to me![p]Forget about going back home! | F920: Ei! Pra onde você tá indo?![p]Aquele Pokémon misterioso! Ele tá me chamando![p]Esquece essa história de voltar pra casa! | G920: 1
A921: english_dp_scenario1 | B921: 9-msg_r201stop_01_1 | C921: Route 201 | E921: Remember what your mother said? | F921: Lembra do que a sua mãe disse? | G921: 1
A922: english_dp_scenario1 | B922: 9-msg_r201stop_01_2 | C922: Route 201 | E922: “[0]! Don’t go into the tall grass. Wild Pokémon might attack you.[p]“It would be OK if you had your own Pokémon, but you don’t, so...” | F922: [0]! Não entre no mato alto. Pokémon selvagens podem atacar você.[p]Tudo bem se você tivesse o seu próprio Pokémon, mas como não tem...' | G922: 1
A923: english_dp_scenario1 | B923: 9-msg_r201_rival_b_04 | C923: Route 201 | D923: Barry | E923: Hey, it’s those people! Is that old guy staring at us? | F923: Ei, são aquelas pessoas! Aquele velhote tá encarando a gente? | G923: 1
A924: english_dp_scenario1 | B924: 9-msg_r201_doctor_b_01_1 | C924: Route 201 | D924: Prof. Rowan | E924: Hmm... | F924: Hmm... | G924: 4
A925: english_dp_scenario1 | B925: 9-msg_r201_doctor_b_01_2 | C925: Route 201 | D925: Prof. Rowan | E925: I heard from [0] that you used our Pokémon? Let me see them, please.[p]Hmm...[p][1] and [2]... | F925: Ouvi dizer por [0] que vocês usaram os nossos Pokémon. Deixem-me vê-los, por favor.[p]Hmm...[p][1] e [2]... | G925: 1
A926: english_dp_scenario1 | B926: 9-msg_r201_doctor_b_01_3 | C926: Route 201 | D926: Prof. Rowan | E926: ...[p]Hmm, I see... That’s how it is... | F926: ...[p]Hmm, entendo... Então é assim... | G926: 1
A927: english_dp_scenario1 | B927: 9-msg_r201_doctor_b_02 | C927: Route 201 | D927: Prof. Rowan | E927: [0]! I’m going back to my lab! | F927: [0]! Estou voltando para o meu laboratório! | G927: 1
A928: english_dp_scenario1 | B928: 9-msg_r201_heroine_b_01 | C928: Route 201 | D928: Dawn (female player) | E928: Um... O-OK! Professor, please wait for me! | F928: Hã... T-tá bom! Professor, espere por mim, por favor! | G928: 1
A929: english_dp_scenario1 | B929: 9-msg_r201_heroine_b_02 | C929: Route 201 | D929: Dawn (female player) | E929: I think you should visit our lab later.[p]OK, see you! | F929: Acho melhor você passar lá no nosso laboratório depois.[p]Certo, até mais! | G929: 1
A930: english_dp_scenario1 | B930: 9-msg_r201_hero_b_01 | C930: Route 201 | D930: Lucas (male player) | E930: Uh... Yeah, of course! Professor, wait for me! | F930: Hã... Sim, claro! Professor, espere por mim! | G930: 1
A931: english_dp_scenario1 | B931: 9-msg_r201_hero_b_02 | C931: Route 201 | D931: Lucas (male player) | E931: You should visit us at our lab later, I think.[p]We’ll be seeing you! | F931: Acho que você devia visitar a gente lá no laboratório depois.[p]A gente se vê! | G931: 1
A932: english_dp_scenario1 | B932: 9-msg_r201_rival_b_05_1 | C932: Route 201 | D932: Barry | E932: What was all that craziness about?[p]I mean, if he was angry, he could’ve just yelled at us, or whatever...[p]And didn’t he want his Pokémon back? | F932: Que loucura foi aquela?[p]Tipo, se ele tava bravo, podia só ter gritado com a gente ou sei lá...[p]E ele não queria o Pokémon dele de volta? | G932: 1
A933: english_dp_scenario1 | B933: 9-msg_r201_rival_b_05_2 | C933: Route 201 | D933: Barry | E933: [0]... We should go home, too... | F933: [0]... Acho melhor a gente ir pra casa também... | G933: 1
A934: english_dp_scenario1 | B934: 9-msg_r201_boy1_01_1 | C934: Route 201 | D934: boy1 | E934: Wild Pokémon lurk in tall grass. They can come bursting out at any time. | F934: Pokémon selvagens se escondem no mato alto. Eles podem saltar na sua frente a qualquer momento. | G934: 1
... A973: english_dp_scenario1 | B973: 10-msg_r202_sign3_01_2 | C973: Route 202 | D973: (sign) | E973: The more your Pokémon battle, the stronger they will become. | F973: Quanto mais os seus Pokémon batalharem, mais fortes eles vão ficar. | G973: 1
A974: english_dp_scenario1 | B974: 11-msg_heroine_01 | D974: Dawn (female player) | E974: Hey, [0]? The professor told me something.[p]He thinks [1] may have reappeared at the Spear Pillar... | F974: Ei, [0]? O professor me contou uma coisa.[p]Ele acha que [1] pode ter reaparecido no Pilar da Lança... | G974: 1
A975: english_dp_scenario1 | B975: 11-msg_heroine_02 | D975: Dawn (female player) | E975: Hi, [0]![p]You’re friends with the elder of Celestic Town, aren’t you?[p]She told me that she had something she wanted to show you. | F975: Oi, [0]![p]Você fez amizade com a anciã da Vila Profecéu, não foi?[p]Ela me disse que tinha uma coisa que queria mostrar para você. | G975: 1
A976: english_dp_scenario1 | B976: 11-msg_heroine_03_1 | D976: Dawn (female player) | E976: Hi, [0]! May I see your Pokédex?[p]... | F976: Oi, [0]! Posso ver a sua Pokédex?[p]... | G976: 1
A977: english_dp_scenario1 | B977: 11-msg_heroine_03_2 | D977: Dawn (female player) | E977: Oh my gosh! You’ve seen every kind of Pokémon in Sinnoh![p]Have you shown your Pokédex to Professor Rowan yet? | F977: Minha nossa! Você já viu todos os tipos de Pokémon de Sinnoh![p]Você já mostrou a sua Pokédex para o Professor Rowan? | G977: 1
A978: english_dp_scenario1 | B978: 11-msg_heroine_04 | D978: Dawn (female player) | E978: Hey, [0], have you ever chatted with my kid sister? | F978: Ei, [0], você já conversou com a minha irmãzinha? | G978: 1
A979: english_dp_scenario1 | B979: 11-msg_heroine_05_1 | D979: Dawn (female player) | E979: Oh, [0], are you acquainted with Bebe? | F979: Ah, [0], você já conhece a Bebe? | G979: 1
A980: english_dp_scenario1 | B980: 11-msg_heroine_05_2 | D980: Dawn (female player) | E980: She lives in Hearthome City.[p]Every Trainer should make it a point to pay Bebe a visit. | F980: Ela mora na Cidade Docelar.[p]Todo Treinador devia fazer questão de dar uma passadinha para visitar a Bebe. | G980: 1
A981: english_dp_scenario1 | B981: 11-msg_heroine_06_1 | D981: Dawn (female player) | E981: Hey! [0], you’ve got a Poké Radar? | F981: Ei! [0], você tem um Pokerradar? | G981: 1
A982: english_dp_scenario1 | B982: 11-msg_heroine_06_2 | D982: Dawn (female player) | E982: Watch for tall grass to rustle wildly when you use your Poké Radar.[p]That could be a sign that a rare Pokémon is hiding in there. | F982: Fique de olho se o mato alto balançar muito forte quando você usar o seu Pokerradar.[p]Pode ser sinal de que há um Pokémon raro se escondendo ali. | G982: 1
A983: english_dp_scenario1 | B983: 11-msg_heroine_07_1 | D983: Dawn (female player) | E983: Hi, [0]! How’s your Poké Radar? | F983: Oi, [0]! Como está indo com o Pokerradar? | G983: 1
A984: english_dp_scenario1 | B984: 11-msg_heroine_07_2 | D984: Dawn (female player) | E984: When you use it, do you sometimes see more than one patch of tall grass rustling?[p]The patch farther away gives you a better chance of seeing the same kind of Pokémon in a row.[p]That’s the feeling I get, anyway. | F984: Quando você o usa, às vezes vê mais de um pedaço de mato alto balançando?[p]O mato que estiver mais longe dá mais chances de encontrar a mesma espécie de Pokémon seguida.[p]Pelo menos é a impressão que eu tenho. | G984: 1
A985: english_dp_scenario1 | B985: 11-msg_heroine_08 | D985: Dawn (female player) | E985: Sometimes a patch of grass sparkles when a Poké Radar is used.[p]People say a Shiny Pokémon is hiding there! Could that be true? | F985: Às vezes, um pedaço do mato brilha quando o Pokerradar é usado.[p]Dizem que há um Pokémon Brilhante escondido ali! Será que é verdade? | G985: 1
... A1008: english_dp_scenario1 | B1008: 11-msg_hero_14 | D1008: Lucas (male player) | E1008: [0], the professor told me the news! Congratulations, Champ! | F1008: [0], o professor me contou a novidade! Parabéns pela vitória na Liga! | G1008: 1
A1009: english_dp_scenario1 | B1009: 12-msg_t02_heroine_01 | C1009: Sandgem Town | D1009: Dawn (female player) | E1009: Oh! There you are! Please, come with me! The professor is waiting! | F1009: Ah! Aí está você! Por favor, venha comigo! O professor está esperando! | G1009: 1
A1010: english_dp_scenario1 | B1010: 12-msg_t02_heroine_02 | C1010: Sandgem Town | D1010: Dawn (female player) | E1010: This is it—our Pokémon Research Lab! Let’s go... | F1010: É aqui: o nosso Laboratório de Pesquisa Pokémon! Vamos entrar... | G1010: 1
A1011: english_dp_scenario1 | B1011: 12-msg_t02_hero_01 | C1011: Sandgem Town | D1011: Lucas (male player) | E1011: Hi! I’ve been waiting for you! Please, come with me. The prof’s waiting to see you. | F1011: Oi! Eu estava esperando você! Por favor, venha comigo. O prof está esperando para falar com você. | G1011: 1
A1012: english_dp_scenario1 | B1012: 12-msg_t02_hero_02 | C1012: Sandgem Town | D1012: Lucas (male player) | E1012: See? This is our Pokémon Research Lab. We’ll just go ahead and... | F1012: Viu só? Este é o nosso Laboratório de Pesquisa Pokémon. Vamos logo entrando e... | G1012: 1
A1013: english_dp_scenario1 | B1013: 12-msg_t02_rival_01 | C1013: Sandgem Town | D1013: Barry | E1013: <size=250%>*thud*</size> | F1013: <size=250%>*bum*</size> | G1013: 6
A1014: english_dp_scenario1 | B1014: 12-msg_t02_rival_02 | C1014: Sandgem Town | D1014: Barry | E1014: What the... Oh, it’s you, [0]![p]That old guy... He’s not scary so much as he is totally out there![p]Aww, it doesn’t matter, [1]. I’m out of here. See you later! | F1014: Mas que... Ah, é você, [0]![p]Aquele velhote... Ele nem dá tanto medo assim, só é meio pancada das ideias![p]Ah, deixa pra lá, [1]. Tô dando o fora daqui. Até mais! | G1014: 1
A1015: english_dp_scenario1 | B1015: 12-msg_t02_heroine_03_1 | C1015: Sandgem Town | D1015: Dawn (female player) | E1015: Wow, what was that? Your friend sure seems to be really impatient. | F1015: Nossa, o que foi isso? Esse seu amigo parece ser muito impaciente. | G1015: 1
A1016: english_dp_scenario1 | B1016: 12-msg_t02_heroine_03_2 | C1016: Sandgem Town | D1016: Dawn (female player) | E1016: Well, anyway... Let’s go inside. | F1016: Bom, enfim... Vamos entrar. | G1016: 1
A1017: english_dp_scenario1 | B1017: 12-msg_t02_hero_03_1 | C1017: Sandgem Town | D1017: Lucas (male player) | E1017: What was that?! Your friend always seems to be in such a rush. | F1017: O que foi isso?! Esse seu amigo parece estar sempre com tanta pressa. | G1017: 1
A1018: english_dp_scenario1 | B1018: 12-msg_t02_hero_03_2 | C1018: Sandgem Town | D1018: Lucas (male player) | E1018: Anyway... Let’s go in. | F1018: Enfim... Vamos entrar. | G1018: 1
A1019: english_dp_scenario1 | B1019: 12-msg_t02_heroine_04_1 | C1019: Sandgem Town | D1019: Dawn (female player) | E1019: OK, [0], I’ll act as your mentor. | F1019: Certo, [0], eu serei a sua mentora. | G1019: 1
A1020: english_dp_scenario1 | B1020: 12-msg_t02_heroine_04_2 | C1020: Sandgem Town | D1020: Dawn (female player) | E1020: I’ve got a bit more experience than you as a Trainer and as the professor’s assistant.[p]OK, follow me! | F1020: Tenho um pouquinho mais de experiência que você como Treinadora e como assistente do professor.[p]Então, siga-me! | G1020: 1
... A1090: english_dp_scenario1 | B1090: 16-msg_t02r0101_bookshelf4_01 | C1090: Sandgem Town | D1090: bookshelf4 | E1090: There’s a lot of reference material and research reports on Pokémon. | F1090: Há muito material de referência e relatórios de pesquisa sobre Pokémon. | G1090: 1
...

Sheet Battle
A1: file | B1: label | C1: location | D1: speaker | E1: english | F1: translation | G1: uses
A2: english_ss_shinka_demo | B2: SS_shinka_demo_01_01 | E2: What? | F2: O quê? | G2: 1
A3: english_ss_shinka_demo | B3: SS_shinka_demo_02_01 | E3: Huh? [0] stopped evolving! | F3: Hã? [0] parou de evoluir! | G3: 1
A4: english_ss_shinka_demo | B4: SS_shinka_demo_03_01 | E4: Congratulations! Your [0] evolved into [1]! | F4: Parabéns! Seu [0] evoluiu para [1]! | G4: 1
A5: english_ss_shinka_demo | B5: SS_shinka_demo_04_01 | E5: [0] learned [1]![e:4][e:1] | F5: [0] aprendeu [1]![e:4][e:1] | G5: 2
A6: english_ss_shinka_demo | B6: SS_shinka_demo_05_01 | E6: One...[w:0.19999998807907104]two...[w:0.19999998807907104]and...[w:0.19999998807907104][w:0.19999998807907104]ta-da![e:3][e:0][p][0] forgot [1]![p]And it learned [2] instead![e:4][e:1] | F6: Um...[w:0.19999998807907104]dois...[w:0.19999998807907104]e...[w:0.19999998807907104][w:0.19999998807907104]tcharam![e:3][e:0][p][0] esqueceu [1]![p]E aprendeu [2] no lugar![e:4][e:1] | G6: 2
A7: english_ss_shinka_demo | B7: SS_shinka_demo_06_01 | E7: [0] did not learn [1]. | F7: [0] não aprendeu [1]. | G7: 3
A8: english_ss_shinka_demo | B8: SS_shinka_demo_07_01 | E8: [0] wants to learn the move [1].[p]Should an old move be forgotten and replaced with [2]? | F8: [0] quer aprender o movimento [1].[p]Deseja esquecer um movimento antigo e substituí-lo por [2]? | G8: 1
A9: english_ss_shinka_demo | B9: SS_shinka_demo_10_01 | E9: Forget an old move | F9: Esquecer um movimento antigo | G9: 3
A10: english_ss_shinka_demo | B10: SS_shinka_demo_10_02 | E10: Keep old moves | F10: Manter os movimentos antigos | G10: 3
A11: english_ss_shinka_demo | B11: SS_shinka_demo_01_02 | E11: [0] is evolving! | F11: [0] está evoluindo! | G11: 1
A12: english_ss_btl_tower_main | B12: SS_btl_tower_main_000 | E12: Battle Tower | F12: Torre de Batalha | G12: 1
A13: english_ss_btl_tower_main | B13: SS_btl_tower_main_001 | E13: Single Battle | F13: Batalha Individual | G13: 2
... A110: english_ss_btl_state | B110: BTR_STATE_02_02 | E110: The rain weather condition. It boosts the power of Water-type moves and lowers the power of Fire-type moves. | F110: A condição climática de chuva. Aumenta o poder dos movimentos de tipo Água e reduz o poder dos movimentos de tipo Fogo. | G110: 1
A111: english_ss_btl_state | B111: BTR_STATE_03_01 | E111: Sandstorm | F111: {=INDEX(Names!$F$2637:$F$3443,MATCH(E111,Names!$E$2637:$E$3443,0))} -> Temp. de Areia | G111: 1
A112: english_ss_btl_state | B112: BTR_STATE_03_02 | E112: The sandstorm weather condition. At the end of each turn, it damages all Pokémon that are not Rock, Ground, or Steel types. It boosts the Sp. Def of Rock-type Pokémon. | F112: A condição climática de tempestade de areia. Ao final de cada turno, causa dano a todos os Pokémon que não sejam de tipo Pedra, Terrestre ou Aço. Aumenta a Def. Esp. dos Pokémon de tipo Pedra. | G112: 1
A113: english_ss_btl_state | B113: BTR_STATE_04_01 | E113: Hail | F113: {=INDEX(Names!$F$2637:$F$3443,MATCH(E113,Names!$E$2637:$E$3443,0))} -> Granizo | G113: 1
A114: english_ss_btl_state | B114: BTR_STATE_04_02 | E114: The hail weather condition. At the end of each turn, it damages all Pokémon that are not Ice types. | F114: A condição climática de granizo. Ao final de cada turno, causa dano a todos os Pokémon que não sejam de tipo Gelo. | G114: 1
A115: english_ss_btl_state | B115: BTR_STATE_08_01 | E115: Trick Room | F115: {=INDEX(Names!$F$2637:$F$3443,MATCH(E115,Names!$E$2637:$E$3443,0))} -> Sala dos Truques | G115: 1
A116: english_ss_btl_state | B116: BTR_STATE_08_02 | E116: Slower Pokémon get to move first for five turns. | F116: Por cinco turnos, os Pokémon mais lentos agem primeiro. | G116: 1
A117: english_ss_btl_state | B117: BTR_STATE_11_01 | E117: Critical Hit Boost | F117: Chance de Crítico Aumentada | G117: 1
A118: english_ss_btl_state | B118: BTR_STATE_11_02 | E118: The Pokémon is more likely to land critical hits. | F118: O Pokémon tem mais chances de acertar golpes críticos. | G118: 1
A119: english_ss_btl_state | B119: BTR_STATE_12_01 | E119: Confusion | F119: Confusão | G119: 1
A120: english_ss_btl_state | B120: BTR_STATE_12_02 | E120: The Pokémon may hurt itself in its confusion. The effect lasts for one to four turns. | F120: O Pokémon pode se ferir na confusão. O efeito dura de um a quatro turnos. | G120: 1
A121: english_ss_btl_state | B121: BTR_STATE_13_01 | E121: Infatuation | F121: Paixão | G121: 1
A122: english_ss_btl_state | B122: BTR_STATE_13_02 | E122: The Pokémon is less likely to unleash an attack on Pokémon of the opposite gender. | F122: O Pokémon tem menos chances de atacar Pokémon do gênero oposto. | G122: 1
A123: english_ss_btl_state | B123: BTR_STATE_05_01 | E123: Electric Terrain | F123: {=INDEX(Names!$F$2637:$F$3443,MATCH(E123,Names!$E$2637:$E$3443,0))} -> Terreno Elétrico | G123: 1
A124: english_ss_btl_state | B124: BTR_STATE_05_02 | E124: For five turns, Pokémon on the ground won’t fall asleep. The power of Electric-type moves is boosted. | F124: Por cinco turnos, os Pokémon no chão não adormecem. O poder dos movimentos de tipo Elétrico aumenta. | G124: 1
A125: english_ss_btl_state | B125: BTR_STATE_16_01 | E125: Encore | F125: {=INDEX(Names!$F$2637:$F$3443,MATCH(E125,Names!$E$2637:$E$3443,0))} -> Bis | G125: 1
A126: english_ss_btl_state | B126: BTR_STATE_16_02 | E126: Due to Encore, the Pokémon can use only [0] for three turns. | F126: ="Devido a "&F125&", o Pokémon só pode usar"&CHAR(10)&"[0] por três turnos." -> Devido a Bis, o Pokémon só pode usar [0] por três turnos. | G126: 1
A127: english_ss_btl_state | B127: BTR_STATE_17_01 | E127: No Ability | F127: Sem Habilidade | G127: 1
A128: english_ss_btl_state | B128: BTR_STATE_17_02 | E128: The Pokémon’s Ability loses its effect. | F128: A Habilidade do Pokémon perde o efeito. | G128: 1
A129: english_ss_btl_state | B129: BTR_STATE_18_01 | E129: Torment | F129: {=INDEX(Names!$F$2637:$F$3443,MATCH(E129,Names!$E$2637:$E$3443,0))} -> Tormento | G129: 1
A130: english_ss_btl_state | B130: BTR_STATE_18_02 | E130: The Pokémon can’t use the same move twice in a row. | F130: O Pokémon não pode usar o mesmo movimento duas vezes seguidas. | G130: 1
A131: english_ss_btl_state | B131: BTR_STATE_19_01 | E131: Tailwind | F131: {=INDEX(Names!$F$2637:$F$3443,MATCH(E131,Names!$E$2637:$E$3443,0))} -> Vento de Cauda | G131: 1
A132: english_ss_btl_state | B132: BTR_STATE_19_02 | E132: The Speed stats of a Pokémon and its allies are doubled for four turns. | F132: A Velocidade do Pokémon e de seus aliados é duplicada por quatro turnos. | G132: 1
A133: english_ss_btl_state | B133: BTR_STATE_21_01 | E133: Grudge | F133: {=INDEX(Names!$F$2637:$F$3443,MATCH(E133,Names!$E$2637:$E$3443,0))} -> Rancor | G133: 1
A134: english_ss_btl_state | B134: BTR_STATE_21_02 | E134: If the Pokémon faints by an opponent’s move, the PP of that move will be reduced to 0. | F134: Se o Pokémon desmaiar devido a um movimento do oponente, os PP desse movimento serão reduzidos a 0. | G134: 1
A135: english_ss_btl_state | B135: BTR_STATE_06_01 | E135: Grassy Terrain | F135: {=INDEX(Names!$F$2637:$F$3443,MATCH(E135,Names!$E$2637:$E$3443,0))} -> Terreno de Grama | G135: 1
A136: english_ss_btl_state | B136: BTR_STATE_06_02 | E136: For five turns, Pokémon on the ground will have a little HP restored at the end of each turn. The power of Grass-type moves is boosted. | F136: Por cinco turnos, os Pokémon no chão recuperam um pouco de PS ao final de cada turno. O poder dos movimentos de tipo Planta aumenta. | G136: 1
A137: english_ss_btl_state | B137: BTR_STATE_07_01 | E137: Misty Terrain | F137: {=INDEX(Names!$F$2637:$F$3443,MATCH(E137,Names!$E$2637:$E$3443,0))} -> Terreno Enevoado | G137: 1
A138: english_ss_btl_state | B138: BTR_STATE_07_02 | E138: For five turns, Pokémon on the ground won’t get any status conditions. Damage from Dragon-type moves is halved. | F138: Por cinco turnos, os Pokémon no chão não sofrem condições de estado. O dano de movimentos de tipo Dragão é reduzido à metade. | G138: 1
A139: english_ss_btl_state | B139: BTR_STATE_24_01 | E139: Move Disabled | F139: Movimento Desabilitado | G139: 1
A140: english_ss_btl_state | B140: BTR_STATE_24_02 | E140: For four turns, the Pokémon will be unable to use [0]. | F140: Por quatro turnos, o Pokémon não poderá usar [0]. | G140: 1
A141: english_ss_btl_state | B141: BTR_STATE_25_01 | E141: Can’t Escape | F141: Não Pode Fugir | G141: 1
A142: english_ss_btl_state | B142: BTR_STATE_25_02 | E142: The Pokémon can’t flee or be switched out. | F142: O Pokémon não pode fugir nem ser substituído. | G142: 1
A143: english_ss_btl_state | B143: BTR_STATE_26_01 | E143: Lock-On | F143: {=INDEX(Names!$F$2637:$F$3443,MATCH(E143,Names!$E$2637:$E$3443,0))} -> Mirar | G143: 2
A144: english_ss_btl_state | B144: BTR_STATE_26_02 | E144: The next move used by the Pokémon will be sure to hit the target that was locked on to. | F144: O próximo movimento usado pelo Pokémon acertará com certeza o alvo na mira. | G144: 1
A145: english_ss_btl_state | B145: BTR_STATE_09_01 | E145: Magic Room | F145: {=INDEX(Names!$F$2637:$F$3443,MATCH(E145,Names!$E$2637:$E$3443,0))} -> Sala Mágica | G145: 1
A146: english_ss_btl_state | B146: BTR_STATE_09_02 | E146: Pokémon can’t use their held items for five turns. | F146: Os Pokémon não podem usar seus itens segurados por cinco turnos. | G146: 1
A147: english_ss_btl_state | B147: BTR_STATE_28_01 | E147: Charge | F147: {=INDEX(Names!$F$2637:$F$3443,MATCH(E147,Names!$E$2637:$E$3443,0))} -> Carga | G147: 1
A148: english_ss_btl_state | B148: BTR_STATE_28_02 | E148: The power of an Electric-type move will be doubled if used in the turn after charging. | F148: O poder de um movimento de tipo Elétrico será duplicado se usado no turno após o carregamento. | G148: 1
A149: english_ss_btl_state | B149: BTR_STATE_29_01 | E149: Gravity | F149: {=INDEX(Names!$F$2637:$F$3443,MATCH(E149,Names!$E$2637:$E$3443,0))} -> Gravidade | G149: 1
A150: english_ss_btl_state | B150: BTR_STATE_29_02 | E150: Moves are more likely to hit for five turns. Ground-type moves will hit Flying-type Pokémon and Pokémon with the Levitate Ability. Moves that require action midair can’t be used. | F150: Os movimentos têm mais chances de acertar por cinco turnos. Movimentos de tipo Terrestre atingem Pokémon de tipo Voador e Pokémon com a Habilidade Levitação. Movimentos que exigem ações no ar não podem ser usados. | G150: 1
A151: english_ss_btl_state | B151: BTR_STATE_30_01 | E151: Mist | F151: {=INDEX(Names!$F$2637:$F$3443,MATCH(E151,Names!$E$2637:$E$3443,0))} -> Neblina | G151: 1
A152: english_ss_btl_state | B152: BTR_STATE_30_02 | E152: The Pokémon’s stats won’t be lowered for five turns. | F152: Os atributos do Pokémon não serão reduzidos por cinco turnos. | G152: 1
A153: english_ss_btl_state | B153: BTR_STATE_31_01 | E153: Safeguard | F153: {=INDEX(Names!$F$2637:$F$3443,MATCH(E153,Names!$E$2637:$E$3443,0))} -> Salvaguarda | G153: 1
A154: english_ss_btl_state | B154: BTR_STATE_31_02 | E154: The Pokémon is protected from status conditions for five turns. | F154: O Pokémon fica protegido de condições de estado por cinco turnos. | G154: 1
A155: english_ss_btl_state | B155: BTR_STATE_32_01 | E155: Stealth Rock | F155: {=INDEX(Names!$F$2637:$F$3443,MATCH(E155,Names!$E$2637:$E$3443,0))} -> Pedra Oculta | G155: 1
A156: english_ss_btl_state | B156: BTR_STATE_32_02 | E156: Pokémon that switch into battle will take damage. | F156: Os Pokémon que entrarem na batalha sofrerão dano. | G156: 1
A157: english_ss_btl_state | B157: BTR_STATE_33_01 | E157: Stockpile | F157: {=INDEX(Names!$F$2637:$F$3443,MATCH(E157,Names!$E$2637:$E$3443,0))} -> Estocagem | G157: 1
A158: english_ss_btl_state | B158: BTR_STATE_33_02 | E158: The Pokémon’s Defense and Sp. Def stats go up while stockpiling. | F158: A Defesa e a Def. Esp. do Pokémon aumentam enquanto ele acumula energia. | G158: 1
A159: english_ss_btl_state | B159: BTR_STATE_34_01 | E159: Taunt | F159: {=INDEX(Names!$F$2637:$F$3443,MATCH(E159,Names!$E$2637:$E$3443,0))} -> Provocação | G159: 1
A160: english_ss_btl_state | B160: BTR_STATE_34_02 | E160: The Pokémon can only use moves that deal damage. | F160: O Pokémon só pode usar movimentos que causam dano. | G160: 1
A161: english_ss_btl_state | B161: BTR_STATE_36_01 | E161: Magnet Rise | F161: {=INDEX(Names!$F$2637:$F$3443,MATCH(E161,Names!$E$2637:$E$3443,0))} -> Eletroelevação | G161: 1
A162: english_ss_btl_state | B162: BTR_STATE_36_02 | E162: Ground-type moves won’t hit the Pokémon for five turns. | F162: Movimentos de tipo Terrestre não atingirão o Pokémon por cinco turnos. | G162: 1
A163: english_ss_btl_state | B163: BTR_STATE_37_01 | E163: Toxic Spikes | F163: {=INDEX(Names!$F$2637:$F$3443,MATCH(E163,Names!$E$2637:$E$3443,0))} -> Espinhos Tóxicos | G163: 1
A164: english_ss_btl_state | B164: BTR_STATE_37_02 | E164: Pokémon that switch into battle will be poisoned. Flying-type Pokémon or Pokémon with the Levitate Ability will not be affected. | F164: Os Pokémon que entrarem na batalha serão envenenados. Pokémon de tipo Voador ou com a Habilidade Levitação não serão afetados. | G164: 1
A165: english_ss_btl_state | B165: BTR_STATE_10_01 | E165: Wonder Room | F165: {=INDEX(Names!$F$2637:$F$3443,MATCH(E165,Names!$E$2637:$E$3443,0))} -> Sala Maravilhosa | G165: 1
A166: english_ss_btl_state | B166: BTR_STATE_10_02 | E166: Pokémon’s Defense and Sp. Def are swapped for five turns. | F166: A Defesa e a Def. Esp. dos Pokémon são trocadas por cinco turnos. | G166: 1
A167: english_ss_btl_state | B167: BTR_STATE_39_01 | E167: Wish | F167: {=INDEX(Names!$F$2637:$F$3443,MATCH(E167,Names!$E$2637:$E$3443,0))} -> Desejo | G167: 1
A168: english_ss_btl_state | B168: BTR_STATE_39_02 | E168: The Pokémon in this spot will have its HP restored on the turn after Wish was used. | F168: ="O Pokémon nesta posição recuperará PS"&CHAR(10)&"no turno seguinte ao uso de "&F167&"." -> O Pokémon nesta posição recuperará PS no turno seguinte ao uso de Desejo. | G168: 1
A169: english_ss_btl_state | B169: BTR_STATE_41_01 | E169: Ingrain | F169: {=INDEX(Names!$F$2637:$F$3443,MATCH(E169,Names!$E$2637:$E$3443,0))} -> Enraizar | G169: 1
A170: english_ss_btl_state | B170: BTR_STATE_41_02 | E170: The Pokémon regains some HP at the end of each turn. Ingrained Pokémon can’t be switched out. | F170: O Pokémon recupera alguns PS ao final de cada turno. Pokémon enraizados não podem ser substituídos. | G170: 1
A171: english_ss_btl_state | B171: BTR_STATE_42_01 | E171: Curse | F171: {=INDEX(Names!$F$2637:$F$3443,MATCH(E171,Names!$E$2637:$E$3443,0))} -> Maldição | G171: 1
A172: english_ss_btl_state | B172: BTR_STATE_42_02 | E172: The Pokémon takes damage at the end of each turn. | F172: O Pokémon sofre dano ao final de cada turno. | G172: 1
A173: english_ss_btl_state | B173: BTR_STATE_15_01 | E173: Drowsy | F173: Sonolento | G173: 1
A174: english_ss_btl_state | B174: BTR_STATE_15_02 | E174: The Pokémon will fall asleep at the end of the turn if it remains on the battlefield. | F174: O Pokémon adormecerá ao final do turno se permanecer no campo de batalha. | G174: 1
A175: english_ss_btl_state | B175: BTR_STATE_44_01 | E175: Light Screen | F175: {=INDEX(Names!$F$2637:$F$3443,MATCH(E175,Names!$E$2637:$E$3443,0))} -> Tela de Luz | G175: 1
A176: english_ss_btl_state | B176: BTR_STATE_44_02 | E176: Damage from special moves is halved for five turns. | F176: O dano de movimentos especiais é reduzido à metade por cinco turnos. | G176: 1
A177: english_ss_btl_state | B177: BTR_STATE_45_01 | E177: Reflect | F177: {=INDEX(Names!$F$2637:$F$3443,MATCH(E177,Names!$E$2637:$E$3443,0))} -> Refletir | G177: 1
A178: english_ss_btl_state | B178: BTR_STATE_45_02 | E178: Damage from physical moves is halved for five turns. | F178: O dano de movimentos físicos é reduzido à metade por cinco turnos. | G178: 1
A179: english_ss_btl_state | B179: BTR_STATE_46_01 | E179: Imprison | F179: {=INDEX(Names!$F$2637:$F$3443,MATCH(E179,Names!$E$2637:$E$3443,0))} -> Aprisionar | G179: 1
A180: english_ss_btl_state | B180: BTR_STATE_46_02 | E180: If a Pokémon affected by Imprison knows any moves also known by the user of Imprison, it is prevented from using those moves. | F180: ="Se um Pokémon afetado por "&F179&" conhecer"&CHAR(10)&"movimentos que o usuário de "&F179&" também conhece,"&CHAR(10)&"ele ficará impedido de usar esses movimentos." -> Se um Pokémon afetado por Aprisionar conhecer movimentos que o usuário de Aprisionar também conhece, ele ficará impedido de usar esses movimentos. | G180: 1
A181: english_ss_btl_state | B181: BTR_STATE_47_01 | E181: Counting Down | F181: Contagem Regressiva | G181: 1
A182: english_ss_btl_state | B182: BTR_STATE_47_02 | E182: All Pokémon in this battle state will faint after three turns. | F182: Todos os Pokémon com este estado de batalha desmaiarão após três turnos. | G182: 1
A183: english_ss_btl_state | B183: BTR_STATE_48_01 | E183: Spikes | F183: {=INDEX(Names!$F$2637:$F$3443,MATCH(E183,Names!$E$2637:$E$3443,0))} -> Espinhos | G183: 1
A184: english_ss_btl_state | B184: BTR_STATE_48_02 | E184: Pokémon that switch into battle will take damage. Flying-type Pokémon or Pokémon with the Levitate Ability will not be affected. | F184: Os Pokémon que entrarem na batalha sofrerão dano. Pokémon de tipo Voador ou com a Habilidade Levitação não serão afetados. | G184: 1
A185: english_ss_btl_state | B185: BTR_STATE_50_01 | E185: Destiny Bond | F185: {=INDEX(Names!$F$2637:$F$3443,MATCH(E185,Names!$E$2637:$E$3443,0))} -> Laço do Destino | G185: 1
A186: english_ss_btl_state | B186: BTR_STATE_50_02 | E186: If the Pokémon is knocked out by an opponent, that opponent will also faint. | F186: Se o Pokémon for nocauteado por um oponente, esse oponente também desmaiará. | G186: 1
A187: english_ss_btl_state | B187: BTR_STATE_40_01 | E187: Sticky Web | F187: {=INDEX(Names!$F$2637:$F$3443,MATCH(E187,Names!$E$2637:$E$3443,0))} -> Teia Viscosa | G187: 1
A188: english_ss_btl_state | B188: BTR_STATE_40_02 | E188: Pokémon that switch into battle will have their Speed lowered. | F188: Os Pokémon que entrarem na batalha terão sua Velocidade reduzida. | G188: 1
A189: english_ss_btl_state | B189: BTR_STATE_52_01 | E189: Leech Seed | F189: {=INDEX(Names!$F$2637:$F$3443,MATCH(E189,Names!$E$2637:$E$3443,0))} -> Semente Drenante | G189: 1
A190: english_ss_btl_state | B190: BTR_STATE_52_02 | E190: Leech Seed steals some of the Pokémon’s HP at the end of each turn and gives it to the opponent. | F190: =F189&" rouba alguns PS do Pokémon"&CHAR(10)&"ao final de cada turno e os transfere"&CHAR(10)&"para o oponente." -> Semente Drenante rouba alguns PS do Pokémon ao final de cada turno e os transfere para o oponente. | G190: 1
A191: english_ss_btl_state | B191: BTR_STATE_53_02 | E191: Any move used against a locked-on target will be sure to hit. | F191: Qualquer movimento usado contra um alvo na mira acertará com certeza. | G191: 1
A192: english_ss_btl_state | B192: BTR_STATE_54_01 | E192: Bound | F192: Preso | G192: 1
A193: english_ss_btl_state | B193: BTR_STATE_54_02 | E193: The Pokémon is bound and takes damage every turn. | F193: O Pokémon está preso e sofre dano a cada turno. | G193: 1
A194: english_ss_btl_state | B194: BTR_STATE_56_01 | E194: Outrage | F194: {=INDEX(Names!$F$2637:$F$3443,MATCH(E194,Names!$E$2637:$E$3443,0))} -> Ultraje | G194: 1
A195: english_ss_btl_state | B195: BTR_STATE_56_02 | E195: The Pokémon rampages and attacks for two to three turns. It then becomes confused. | F195: O Pokémon entra em fúria e ataca por dois a três turnos. Depois, fica confuso. | G195: 3
A196: english_ss_btl_state | B196: BTR_STATE_57_01 | E196: Rampaging | F196: Em Fúria | G196: 1
...

Sheet Credits & Misc
A1: file | B1: label | C1: location | D1: speaker | E1: english | F1: translation | G1: uses
A2: english_dlp_halloffame_demo | B2: DLP_halloffame_demo_015 | E2: Lv. [0] | F2: Nv. [0] | G2: 1
A3: english_dlp_halloffame_demo | B3: DLP_halloffame_demo_013 | E3: [0] ID: [1] Time: [2]:[3] | F3: [0] ID: [1] Tempo: [2]:[3] | G3: 1
A4: english_dlp_staff_list | B4: DLP_staff_list_001 | E4: Pokémon Brilliant Diamond | F4: Pokémon Diamante Brilhante | G4: 1
A5: english_dlp_staff_list | B5: DLP_staff_list_002 | E5: Pokémon Shining Pearl | F5: Pokémon Pérola Reluzente | G5: 1
A6: english_dlp_staff_list | B6: DLP_staff_list_003 | E6: STAFF | F6: EQUIPE | G6: 1
A7: english_dlp_staff_list | B7: DLP_staff_list_004 | E7: DIRECTOR | F7: DIREÇÃO | G7: 2
A8: english_dlp_staff_list | B8: DLP_staff_list_005 | E8: Yuichi Ueda | F8: Yuichi Ueda | G8: 1
A9: english_dlp_staff_list | B9: DLP_staff_list_007 | E9: Junichi Masuda | F9: Junichi Masuda | G9: 3
A10: english_dlp_staff_list | B10: DLP_staff_list_008 | E10: 3D GRAPHIC MANAGER | F10: GERÊNCIA DE GRÁFICOS 3D | G10: 1
A11: english_dlp_staff_list | B11: DLP_staff_list_009 | E11: Takahiro Mizutani | F11: Takahiro Mizutani | G11: 1
A12: english_dlp_staff_list | B12: DLP_staff_list_010 | E12: PROGRAM LEADER | F12: LIDERANÇA DE PROGRAMAÇÃO | G12: 1
A13: english_dlp_staff_list | B13: DLP_staff_list_011 | E13: Shinya Suda | F13: Shinya Suda | G13: 1
... A599: english_ss_zkn_weight | B599: ZKN_WEIGHT_000_000 | E599: ????.? lbs. | F599: ????,? kg | G599: 1
A600: english_ss_zkn_weight | B600: ZKN_WEIGHT_001_000 | E600: 15.2 lbs. | F600: =SUBSTITUTE(TEXT(VALUE(SUBSTITUTE(LEFT(E600,LEN(E600)-5),".",","))*45359237/100000000,"0.0"),".",",")&" kg" -> 6,9 kg | G600: 2
A601: english_ss_zkn_weight | B601: ZKN_WEIGHT_002_000 | E601: 28.7 lbs. | F601: =SUBSTITUTE(TEXT(VALUE(SUBSTITUTE(LEFT(E601,LEN(E601)-5),".",","))*45359237/100000000,"0.0"),".",",")&" kg" -> 13,0 kg | G601: 8
A602: english_ss_zkn_weight | B602: ZKN_WEIGHT_003_000 | E602: 220.5 lbs. | F602: =SUBSTITUTE(TEXT(VALUE(SUBSTITUTE(LEFT(E602,LEN(E602)-5),".",","))*45359237/100000000,"0.0"),".",",")&" kg" -> 100,0 kg | G602: 7
A603: english_ss_zkn_weight | B603: ZKN_WEIGHT_004_000 | E603: 18.7 lbs. | F603: =SUBSTITUTE(TEXT(VALUE(SUBSTITUTE(LEFT(E603,LEN(E603)-5),".",","))*45359237/100000000,"0.0"),".",",")&" kg" -> 8,5 kg | G603: 11
A604: english_ss_zkn_weight | B604: ZKN_WEIGHT_005_000 | E604: 41.9 lbs. | F604: =SUBSTITUTE(TEXT(VALUE(SUBSTITUTE(LEFT(E604,LEN(E604)-5),".",","))*45359237/100000000,"0.0"),".",",")&" kg" -> 19,0 kg | G604: 5
A605: english_ss_zkn_weight | B605: ZKN_WEIGHT_006_000 | E605: 199.5 lbs. | F605: =SUBSTITUTE(TEXT(VALUE(SUBSTITUTE(LEFT(E605,LEN(E605)-5),".",","))*45359237/100000000,"0.0"),".",",")&" kg" -> 90,5 kg | G605: 3
A606: english_ss_zkn_weight | B606: ZKN_WEIGHT_007_000 | E606: 19.8 lbs. | F606: =SUBSTITUTE(TEXT(VALUE(SUBSTITUTE(LEFT(E606,LEN(E606)-5),".",","))*45359237/100000000,"0.0"),".",",")&" kg" -> 9,0 kg | G606: 7
A607: english_ss_zkn_weight | B607: ZKN_WEIGHT_008_000 | E607: 49.6 lbs. | F607: =SUBSTITUTE(TEXT(VALUE(SUBSTITUTE(LEFT(E607,LEN(E607)-5),".",","))*45359237/100000000,"0.0"),".",",")&" kg" -> 22,5 kg | G607: 2
A608: english_ss_zkn_weight | B608: ZKN_WEIGHT_009_000 | E608: 188.5 lbs. | F608: =SUBSTITUTE(TEXT(VALUE(SUBSTITUTE(LEFT(E608,LEN(E608)-5),".",","))*45359237/100000000,"0.0"),".",",")&" kg" -> 85,5 kg | G608: 3
A609: english_ss_zkn_weight | B609: ZKN_WEIGHT_010_000 | E609: 6.4 lbs. | F609: =SUBSTITUTE(TEXT(VALUE(SUBSTITUTE(LEFT(E609,LEN(E609)-5),".",","))*45359237/100000000,"0.0"),".",",")&" kg" -> 2,9 kg | G609: 1
A610: english_ss_zkn_weight | B610: ZKN_WEIGHT_011_000 | E610: 21.8 lbs. | F610: =SUBSTITUTE(TEXT(VALUE(SUBSTITUTE(LEFT(E610,LEN(E610)-5),".",","))*45359237/100000000,"0.0"),".",",")&" kg" -> 9,9 kg | G610: 4
A611: english_ss_zkn_weight | B611: ZKN_WEIGHT_012_000 | E611: 70.5 lbs. | F611: =SUBSTITUTE(TEXT(VALUE(SUBSTITUTE(LEFT(E611,LEN(E611)-5),".",","))*45359237/100000000,"0.0"),".",",")&" kg" -> 32,0 kg | G611: 6
... A1081: english_ss_zkn_weight | B1081: ZKN_WEIGHT_898_002 | E1081: 118.2 lbs. | F1081: =SUBSTITUTE(TEXT(VALUE(SUBSTITUTE(LEFT(E1081,LEN(E1081)-5),".",","))*45359237/100000000,"0.0"),".",",")&" kg" -> 53,6 kg | G1081: 1

Sheet Verificação
A1: REVISÃO FINAL — TERMOS E INTEGRIDADE
A2: Aba | B2: Linhas | C2: Traduções vazias | D2: Erros | E2: [0] | F2: [1] | G2: [2] | H2: [3] | I2: [p] | J2: [s] | K2: </color> | L2: [4] | M2: [5] | N2: [6] | O2: [7] | P2: [8] | Q2: [9] | R2: <color= | S2: [e: | T2: [w:
A3: Menus & UI | B3: 1960 | C3: =COUNTIFS('Menus & UI'!E2:E1961,"<>",'Menus & UI'!F2:F1961,"") -> 0 | D3: =SUMPRODUCT(--ISERROR('Menus & UI'!F2:F1961)) -> 0 | E3: =SUMPRODUCT(--((LEN('Menus & UI'!$E$2:$E$1961)-LEN(SUBSTITUTE('Menus & UI'!$E$2:$E$1961,E$2,"")))<>(LEN('Menus & UI'!$F$2:$F$1961)-LEN(SUBSTITUTE('Menus & UI'!$F$2:$F$1961,E$2,""))))) -> 0 | F3: =SUMPRODUCT(--((LEN('Menus & UI'!$E$2:$E$1961)-LEN(SUBSTITUTE('Menus & UI'!$E$2:$E$1961,F$2,"")))<>(LEN('Menus & UI'!$F$2:$F$1961)-LEN(SUBSTITUTE('Menus & UI'!$F$2:$F$1961,F$2,""))))) -> 0 | G3: =SUMPRODUCT(--((LEN('Menus & UI'!$E$2:$E$1961)-LEN(SUBSTITUTE('Menus & UI'!$E$2:$E$1961,G$2,"")))<>(LEN('Menus & UI'!$F$2:$F$1961)-LEN(SUBSTITUTE('Menus & UI'!$F$2:$F$1961,G$2,""))))) -> 0 | H3: =SUMPRODUCT(--((LEN('Menus & UI'!$E$2:$E$1961)-LEN(SUBSTITUTE('Menus & UI'!$E$2:$E$1961,H$2,"")))<>(LEN('Menus & UI'!$F$2:$F$1961)-LEN(SUBSTITUTE('Menus & UI'!$F$2:$F$1961,H$2,""))))) -> 0 | I3: =SUMPRODUCT(--((LEN('Menus & UI'!$E$2:$E$1961)-LEN(SUBSTITUTE('Menus & UI'!$E$2:$E$1961,I$2,"")))<>(LEN('Menus & UI'!$F$2:$F$1961)-LEN(SUBSTITUTE('Menus & UI'!$F$2:$F$1961,I$2,""))))) -> 0 | J3: =SUMPRODUCT(--((LEN('Menus & UI'!$E$2:$E$1961)-LEN(SUBSTITUTE('Menus & UI'!$E$2:$E$1961,J$2,"")))<>(LEN('Menus & UI'!$F$2:$F$1961)-LEN(SUBSTITUTE('Menus & UI'!$F$2:$F$1961,J$2,""))))) -> 0 | K3: =SUMPRODUCT(--((LEN('Menus & UI'!$E$2:$E$1961)-LEN(SUBSTITUTE('Menus & UI'!$E$2:$E$1961,K$2,"")))<>(LEN('Menus & UI'!$F$2:$F$1961)-LEN(SUBSTITUTE('Menus & UI'!$F$2:$F$1961,K$2,""))))) -> 0 | L3: =SUMPRODUCT(--((LEN('Menus & UI'!$E$2:$E$1961)-LEN(SUBSTITUTE('Menus & UI'!$E$2:$E$1961,L$2,"")))<>(LEN('Menus & UI'!$F$2:$F$1961)-LEN(SUBSTITUTE('Menus & UI'!$F$2:$F$1961,L$2,""))))) -> 0 | ... T3: =SUMPRODUCT(--((LEN('Menus & UI'!$E$2:$E$1961)-LEN(SUBSTITUTE('Menus & UI'!$E$2:$E$1961,T$2,"")))<>(LEN('Menus & UI'!$F$2:$F$1961)-LEN(SUBSTITUTE('Menus & UI'!$F$2:$F$1961,T$2,""))))) -> 0
A4: Descriptions | B4: 3511 | C4: =COUNTIFS(Descriptions!E2:E3512,"<>",Descriptions!F2:F3512,"") -> 0 | D4: =SUMPRODUCT(--ISERROR(Descriptions!F2:F3512)) -> 0 | E4: =SUMPRODUCT(--((LEN(Descriptions!$E$2:$E$3512)-LEN(SUBSTITUTE(Descriptions!$E$2:$E$3512,E$2,"")))<>(LEN(Descriptions!$F$2:$F$3512)-LEN(SUBSTITUTE(Descriptions!$F$2:$F$3512,E$2,""))))) -> 0 | F4: =SUMPRODUCT(--((LEN(Descriptions!$E$2:$E$3512)-LEN(SUBSTITUTE(Descriptions!$E$2:$E$3512,F$2,"")))<>(LEN(Descriptions!$F$2:$F$3512)-LEN(SUBSTITUTE(Descriptions!$F$2:$F$3512,F$2,""))))) -> 0 | G4: =SUMPRODUCT(--((LEN(Descriptions!$E$2:$E$3512)-LEN(SUBSTITUTE(Descriptions!$E$2:$E$3512,G$2,"")))<>(LEN(Descriptions!$F$2:$F$3512)-LEN(SUBSTITUTE(Descriptions!$F$2:$F$3512,G$2,""))))) -> 0 | H4: =SUMPRODUCT(--((LEN(Descriptions!$E$2:$E$3512)-LEN(SUBSTITUTE(Descriptions!$E$2:$E$3512,H$2,"")))<>(LEN(Descriptions!$F$2:$F$3512)-LEN(SUBSTITUTE(Descriptions!$F$2:$F$3512,H$2,""))))) -> 0 | I4: =SUMPRODUCT(--((LEN(Descriptions!$E$2:$E$3512)-LEN(SUBSTITUTE(Descriptions!$E$2:$E$3512,I$2,"")))<>(LEN(Descriptions!$F$2:$F$3512)-LEN(SUBSTITUTE(Descriptions!$F$2:$F$3512,I$2,""))))) -> 0 | J4: =SUMPRODUCT(--((LEN(Descriptions!$E$2:$E$3512)-LEN(SUBSTITUTE(Descriptions!$E$2:$E$3512,J$2,"")))<>(LEN(Descriptions!$F$2:$F$3512)-LEN(SUBSTITUTE(Descriptions!$F$2:$F$3512,J$2,""))))) -> 0 | K4: =SUMPRODUCT(--((LEN(Descriptions!$E$2:$E$3512)-LEN(SUBSTITUTE(Descriptions!$E$2:$E$3512,K$2,"")))<>(LEN(Descriptions!$F$2:$F$3512)-LEN(SUBSTITUTE(Descriptions!$F$2:$F$3512,K$2,""))))) -> 0 | L4: =SUMPRODUCT(--((LEN(Descriptions!$E$2:$E$3512)-LEN(SUBSTITUTE(Descriptions!$E$2:$E$3512,L$2,"")))<>(LEN(Descriptions!$F$2:$F$3512)-LEN(SUBSTITUTE(Descriptions!$F$2:$F$3512,L$2,""))))) -> 0 | ... T4: =SUMPRODUCT(--((LEN(Descriptions!$E$2:$E$3512)-LEN(SUBSTITUTE(Descriptions!$E$2:$E$3512,T$2,"")))<>(LEN(Descriptions!$F$2:$F$3512)-LEN(SUBSTITUTE(Descriptions!$F$2:$F$3512,T$2,""))))) -> 0
A5: Dialogue | B5: 9613 | C5: =COUNTIFS(Dialogue!E2:E9614,"<>",Dialogue!F2:F9614,"") -> 0 | D5: =SUMPRODUCT(--ISERROR(Dialogue!F2:F9614)) -> 0 | E5: =SUMPRODUCT(--((LEN(Dialogue!$E$2:$E$9614)-LEN(SUBSTITUTE(Dialogue!$E$2:$E$9614,E$2,"")))<>(LEN(Dialogue!$F$2:$F$9614)-LEN(SUBSTITUTE(Dialogue!$F$2:$F$9614,E$2,""))))) -> 0 | F5: =SUMPRODUCT(--((LEN(Dialogue!$E$2:$E$9614)-LEN(SUBSTITUTE(Dialogue!$E$2:$E$9614,F$2,"")))<>(LEN(Dialogue!$F$2:$F$9614)-LEN(SUBSTITUTE(Dialogue!$F$2:$F$9614,F$2,""))))) -> 0 | G5: =SUMPRODUCT(--((LEN(Dialogue!$E$2:$E$9614)-LEN(SUBSTITUTE(Dialogue!$E$2:$E$9614,G$2,"")))<>(LEN(Dialogue!$F$2:$F$9614)-LEN(SUBSTITUTE(Dialogue!$F$2:$F$9614,G$2,""))))) -> 0 | H5: =SUMPRODUCT(--((LEN(Dialogue!$E$2:$E$9614)-LEN(SUBSTITUTE(Dialogue!$E$2:$E$9614,H$2,"")))<>(LEN(Dialogue!$F$2:$F$9614)-LEN(SUBSTITUTE(Dialogue!$F$2:$F$9614,H$2,""))))) -> 0 | I5: =SUMPRODUCT(--((LEN(Dialogue!$E$2:$E$9614)-LEN(SUBSTITUTE(Dialogue!$E$2:$E$9614,I$2,"")))<>(LEN(Dialogue!$F$2:$F$9614)-LEN(SUBSTITUTE(Dialogue!$F$2:$F$9614,I$2,""))))) -> 0 | J5: =SUMPRODUCT(--((LEN(Dialogue!$E$2:$E$9614)-LEN(SUBSTITUTE(Dialogue!$E$2:$E$9614,J$2,"")))<>(LEN(Dialogue!$F$2:$F$9614)-LEN(SUBSTITUTE(Dialogue!$F$2:$F$9614,J$2,""))))) -> 0 | K5: =SUMPRODUCT(--((LEN(Dialogue!$E$2:$E$9614)-LEN(SUBSTITUTE(Dialogue!$E$2:$E$9614,K$2,"")))<>(LEN(Dialogue!$F$2:$F$9614)-LEN(SUBSTITUTE(Dialogue!$F$2:$F$9614,K$2,""))))) -> 0 | L5: =SUMPRODUCT(--((LEN(Dialogue!$E$2:$E$9614)-LEN(SUBSTITUTE(Dialogue!$E$2:$E$9614,L$2,"")))<>(LEN(Dialogue!$F$2:$F$9614)-LEN(SUBSTITUTE(Dialogue!$F$2:$F$9614,L$2,""))))) -> 0 | ... T5: =SUMPRODUCT(--((LEN(Dialogue!$E$2:$E$9614)-LEN(SUBSTITUTE(Dialogue!$E$2:$E$9614,T$2,"")))<>(LEN(Dialogue!$F$2:$F$9614)-LEN(SUBSTITUTE(Dialogue!$F$2:$F$9614,T$2,""))))) -> 0
A6: Battle | B6: 5350 | C6: =COUNTIFS(Battle!E2:E5351,"<>",Battle!F2:F5351,"") -> 0 | D6: =SUMPRODUCT(--ISERROR(Battle!F2:F5351)) -> 0 | E6: =SUMPRODUCT(--((LEN(Battle!$E$2:$E$5351)-LEN(SUBSTITUTE(Battle!$E$2:$E$5351,E$2,"")))<>(LEN(Battle!$F$2:$F$5351)-LEN(SUBSTITUTE(Battle!$F$2:$F$5351,E$2,""))))) -> 0 | F6: =SUMPRODUCT(--((LEN(Battle!$E$2:$E$5351)-LEN(SUBSTITUTE(Battle!$E$2:$E$5351,F$2,"")))<>(LEN(Battle!$F$2:$F$5351)-LEN(SUBSTITUTE(Battle!$F$2:$F$5351,F$2,""))))) -> 0 | G6: =SUMPRODUCT(--((LEN(Battle!$E$2:$E$5351)-LEN(SUBSTITUTE(Battle!$E$2:$E$5351,G$2,"")))<>(LEN(Battle!$F$2:$F$5351)-LEN(SUBSTITUTE(Battle!$F$2:$F$5351,G$2,""))))) -> 0 | H6: =SUMPRODUCT(--((LEN(Battle!$E$2:$E$5351)-LEN(SUBSTITUTE(Battle!$E$2:$E$5351,H$2,"")))<>(LEN(Battle!$F$2:$F$5351)-LEN(SUBSTITUTE(Battle!$F$2:$F$5351,H$2,""))))) -> 0 | I6: =SUMPRODUCT(--((LEN(Battle!$E$2:$E$5351)-LEN(SUBSTITUTE(Battle!$E$2:$E$5351,I$2,"")))<>(LEN(Battle!$F$2:$F$5351)-LEN(SUBSTITUTE(Battle!$F$2:$F$5351,I$2,""))))) -> 0 | J6: =SUMPRODUCT(--((LEN(Battle!$E$2:$E$5351)-LEN(SUBSTITUTE(Battle!$E$2:$E$5351,J$2,"")))<>(LEN(Battle!$F$2:$F$5351)-LEN(SUBSTITUTE(Battle!$F$2:$F$5351,J$2,""))))) -> 0 | K6: =SUMPRODUCT(--((LEN(Battle!$E$2:$E$5351)-LEN(SUBSTITUTE(Battle!$E$2:$E$5351,K$2,"")))<>(LEN(Battle!$F$2:$F$5351)-LEN(SUBSTITUTE(Battle!$F$2:$F$5351,K$2,""))))) -> 0 | L6: =SUMPRODUCT(--((LEN(Battle!$E$2:$E$5351)-LEN(SUBSTITUTE(Battle!$E$2:$E$5351,L$2,"")))<>(LEN(Battle!$F$2:$F$5351)-LEN(SUBSTITUTE(Battle!$F$2:$F$5351,L$2,""))))) -> 0 | ... T6: =SUMPRODUCT(--((LEN(Battle!$E$2:$E$5351)-LEN(SUBSTITUTE(Battle!$E$2:$E$5351,T$2,"")))<>(LEN(Battle!$F$2:$F$5351)-LEN(SUBSTITUTE(Battle!$F$2:$F$5351,T$2,""))))) -> 0
A7: Credits & Misc | B7: 1080 | C7: =COUNTIFS('Credits & Misc'!E2:E1081,"<>",'Credits & Misc'!F2:F1081,"") -> 0 | D7: =SUMPRODUCT(--ISERROR('Credits & Misc'!F2:F1081)) -> 0 | E7: =SUMPRODUCT(--((LEN('Credits & Misc'!$E$2:$E$1081)-LEN(SUBSTITUTE('Credits & Misc'!$E$2:$E$1081,E$2,"")))<>(LEN('Credits & Misc'!$F$2:$F$1081)-LEN(SUBSTITUTE('Credits & Misc'!$F$2:$F$1081,E$2,""))))) -> 0 | F7: =SUMPRODUCT(--((LEN('Credits & Misc'!$E$2:$E$1081)-LEN(SUBSTITUTE('Credits & Misc'!$E$2:$E$1081,F$2,"")))<>(LEN('Credits & Misc'!$F$2:$F$1081)-LEN(SUBSTITUTE('Credits & Misc'!$F$2:$F$1081,F$2,""))))) -> 0 | G7: =SUMPRODUCT(--((LEN('Credits & Misc'!$E$2:$E$1081)-LEN(SUBSTITUTE('Credits & Misc'!$E$2:$E$1081,G$2,"")))<>(LEN('Credits & Misc'!$F$2:$F$1081)-LEN(SUBSTITUTE('Credits & Misc'!$F$2:$F$1081,G$2,""))))) -> 0 | H7: =SUMPRODUCT(--((LEN('Credits & Misc'!$E$2:$E$1081)-LEN(SUBSTITUTE('Credits & Misc'!$E$2:$E$1081,H$2,"")))<>(LEN('Credits & Misc'!$F$2:$F$1081)-LEN(SUBSTITUTE('Credits & Misc'!$F$2:$F$1081,H$2,""))))) -> 0 | I7: =SUMPRODUCT(--((LEN('Credits & Misc'!$E$2:$E$1081)-LEN(SUBSTITUTE('Credits & Misc'!$E$2:$E$1081,I$2,"")))<>(LEN('Credits & Misc'!$F$2:$F$1081)-LEN(SUBSTITUTE('Credits & Misc'!$F$2:$F$1081,I$2,""))))) -> 0 | J7: =SUMPRODUCT(--((LEN('Credits & Misc'!$E$2:$E$1081)-LEN(SUBSTITUTE('Credits & Misc'!$E$2:$E$1081,J$2,"")))<>(LEN('Credits & Misc'!$F$2:$F$1081)-LEN(SUBSTITUTE('Credits & Misc'!$F$2:$F$1081,J$2,""))))) -> 0 | K7: =SUMPRODUCT(--((LEN('Credits & Misc'!$E$2:$E$1081)-LEN(SUBSTITUTE('Credits & Misc'!$E$2:$E$1081,K$2,"")))<>(LEN('Credits & Misc'!$F$2:$F$1081)-LEN(SUBSTITUTE('Credits & Misc'!$F$2:$F$1081,K$2,""))))) -> 0 | L7: =SUMPRODUCT(--((LEN('Credits & Misc'!$E$2:$E$1081)-LEN(SUBSTITUTE('Credits & Misc'!$E$2:$E$1081,L$2,"")))<>(LEN('Credits & Misc'!$F$2:$F$1081)-LEN(SUBSTITUTE('Credits & Misc'!$F$2:$F$1081,L$2,""))))) -> 0 | ... T7: =SUMPRODUCT(--((LEN('Credits & Misc'!$E$2:$E$1081)-LEN(SUBSTITUTE('Credits & Misc'!$E$2:$E$1081,T$2,"")))<>(LEN('Credits & Misc'!$F$2:$F$1081)-LEN(SUBSTITUTE('Credits & Misc'!$F$2:$F$1081,T$2,""))))) -> 0
A9: Marcadores: números indicam quantas linhas diferem do original na quantidade do marcador.
A10: Controles de marcadores verificam quantidades; a apresentação e os parâmetros completos ainda precisam de teste no jogo.
A11: Referências: Names e Página1; preservar nomes próprios e termos sem localização definida.
A12: Data da revisão: 2026-10-18
A14: Naturezas — divergências com Página1
A15: Names | B15: =SUMPRODUCT(--(Names!F3711:F3735<>'Página1'!M4:M28)) -> 25
A16: Menus & UI | B16: =SUMPRODUCT(--('Menus & UI'!F1243:F1267<>'Página1'!M4:M28)) -> 25
A17: Descriptions | B17: =SUMPRODUCT(--(Descriptions!F2:F26<>("Este Pokémon tem uma natureza bem <color=#F01E1EFF>"&'Página1'!M4:M28&"</color>."))) -> 25
A19: Linhas verificadas | B19: =SUM(B3:B7) -> 21514
A21: Correções: 212 traduções vazias em Battle; termos de itens, movimentos e locais; marcadores em Dialogue e Descriptions.
A22: Escopo: preenchimento, erros, quantidade dos marcadores listados e buscas terminológicas direcionadas. Não substitui teste visual no jogo.
A23: Resultado: nenhuma lacuna de tradução ou erro de célula; quantidades dos marcadores listados coincidem com o original.

Sheet Página1
A2: TWINLEAF TOWN | C2: VILA FOLHAPAR
A3: SANDGEM TOWN | C3: VILA FINAREIA
A4: JUBILIFE CITY | C4: CIDADE VIDALEGRE
A5: OREBURGH CITY | C5: CIDADE MINECÍPIO
A6: FLOAROMA TOWN | C6: VILA FLORAROMA
A7: ETERNA CITY | C7: CIDADE VELHENDA
A8: HEARTHOME CITY | C8: CIDADE DOCELAR
A9: SOLACEON TOWN | C9: VILA RUINIRVA
A10: VEILSTONE CITY | C10: CIDADE ROCHAVÉU
A11: PASTORIA CITY | C11: CIDADE PASTONAL
A12: CELESTIC TOWN | C12: VILA PROFECÉU
A13: CANALAVE CITY | C13: CIDADE CANALEITO
... A64: RAMANAS PARK | C64: PARQUE ROSA RUGOSA
